{
  "shadow": {
    "medium": {
      "type": "shadow",
      "value": "0px 1px 2px 0px rgba(49, 55, 58, 0.08), 0px 1px 4px 0px rgba(49, 55, 58, 0.08), 0px 2px 8px 0px rgba(49, 55, 58, 0.08)"
    },
    "large": {
      "type": "shadow",
      "value": "0px 0px 3px 0px rgba(49, 55, 58, 0.12), 0px 2px 6px 0px rgba(49, 55, 58, 0.12), 0px 3px 8px 0px rgba(49, 55, 58, 0.16)"
    },
    "x-large": {
      "type": "shadow",
      "value": "0px 1px 4px 0px rgba(49, 55, 58, 0.12), 0px 8px 24px 0px rgba(49, 55, 58, 0.12), 0px 16px 48px 0px rgba(49, 55, 58, 0.16)"
    },
    "overflow-down": {
      "comment": "Overflow Down",
      "type": "shadow",
      "value": "0px 1px 4px 0px rgba(49, 55, 58, 0.12), 0px 3px 8px 0px rgba(49, 55, 58, 0.12), 0px 4px 12px 0px rgba(49, 55, 58, 0.16)"
    },
    "overflow-up": {
      "comment": "Overflow Up",
      "type": "shadow",
      "value": "0px -1px 4px 0px rgba(49, 55, 58, 0.12), 0px -3px 8px 0px rgba(49, 55, 58, 0.12), 0px -4px 12px 0px rgba(49, 55, 58, 0.16)"
    },
    "overflow-left": {
      "comment": "Overflow Left",
      "type": "shadow",
      "value": "-1px 0px 4px 0px rgba(49, 55, 58, 0.12), -3px 0px 8px 0px rgba(49, 55, 58, 0.12), -4px 0px 12px 0px rgba(49, 55, 58, 0.16)"
    },
    "overflow-right": {
      "comment": "Overflow Right",
      "type": "shadow",
      "value": "1px 0px 4px 0px rgba(49, 55, 58, 0.12), 3px 0px 8px 0px rgba(49, 55, 58, 0.12), 4px 0px 12px 0px rgba(49, 55, 58, 0.16)"
    },
    "x-small": {
      "comment": "Shoelace compatibility DO NOT USE",
      "type": "shadow",
      "value": "0px 1px 2px 0px rgba(49, 55, 58, 0.04), 0px 1px 4px 0px rgba(49, 55, 58, 0.04), 0px 2px 8px 0px rgba(49, 55, 58, 0.04)"
    },
    "small": {
      "comment": "Shoelace compatibility DO NOT USE",
      "type": "shadow",
      "value": "0px 1px 2px 0px rgba(49, 55, 58, 0.06), 0px 1px 4px 0px rgba(49, 55, 58, 0.06), 0px 2px 8px 0px rgba(49, 55, 58, 0.06)"
    }
  },
  "body": {
    "x-small": {
      "regular": {
        "type": "typography",
        "value": "{font-weight.normal} {font-size.x-small}/1.4 {font.sans}"
      },
      "semibold": {
        "type": "typography",
        "value": "{font-weight.semibold} {font-size.x-small}/1.4 {font.sans}"
      },
      "bold": {
        "type": "typography",
        "value": "{font-weight.bold} {font-size.x-small}/1.4 {font.sans}"
      }
    },
    "small": {
      "regular": {
        "type": "typography",
        "value": "{font-weight.normal} {font-size.small}/1.4 {font.sans}"
      },
      "semibold": {
        "type": "typography",
        "value": "{font-weight.semibold} {font-size.small}/1.4 {font.sans}"
      },
      "bold": {
        "type": "typography",
        "value": "{font-weight.bold} {font-size.small}/1.4 {font.sans}"
      }
    },
    "medium": {
      "regular": {
        "type": "typography",
        "value": "{font-weight.normal} {font-size.medium}/1.4 {font.sans}"
      },
      "semibold": {
        "type": "typography",
        "value": "{font-weight.semibold} {font-size.medium}/1.4 {font.sans}"
      },
      "bold": {
        "type": "typography",
        "value": "{font-weight.bold} {font-size.medium}/1.4 {font.sans}"
      }
    },
    "large": {
      "regular": {
        "type": "typography",
        "value": "{font-weight.normal} {font-size.large}/1.4 {font.sans}"
      },
      "semibold": {
        "type": "typography",
        "value": "{font-weight.semibold} {font-size.large}/1.4 {font.sans}"
      },
      "bold": {
        "type": "typography",
        "value": "{font-weight.bold} {font-size.large}/1.4 {font.sans}"
      }
    }
  },
  "heading": {
    "large": {
      "type": "typography",
      "value": "{font-weight.bold} {font-size.large}/1.4 {font.sans}"
    },
    "x-large": {
      "type": "typography",
      "value": "{font-weight.bold} {font-size.x-large}/1.2 {font.sans}"
    },
    "2x-large": {
      "type": "typography",
      "value": "{font-weight.bold} {font-size.2x-large}/1.2 {font.sans}"
    },
    "3x-large": {
      "type": "typography",
      "value": "{font-weight.bold} {font-size.3x-large}/1.2 {font.sans}"
    }
  }
}